{
    "partID": -1,
    "partName": "Scythe Blade",
    "levelRequirement": 25,
    "validMaterials": [
        "Adamantine",
        "Bronze",
        "Copper",
        "Iron",
        "Mythril",
        "Silver",
        "Steel"
    ],
    "validMaterialTypes": [
        "Metal"
    ],
    "unitsOfMaterialNeeded": 3,
    "baseCost": 15,
    "baseStrength": 3,
    "baseDextarity": 1,
    "baseIntelligence": 0,
    "filters": [
        "Parts Only",
        "Metal",
        "Subtype - Magical Metal",
        "Subtype - Non-Magical Metal"
    ]
}